{
    "total":2,
    "totalHits":2,
    "hits":[
        {
            "id":1,
            "webformatURL":"https://wx1.sinaimg.cn/orj360/ecf58dbdgy1fkbwt72pdej20k00segpv.jpg",
            "webformatWidth":640,
            "webformatHeight":640,
            "largeImageURL":"https://wx1.sinaimg.cn/mw1024/ecf58dbdgy1fkbwt72pdej20k00segpv.jpg",
            "favorites":0,
            "user":"9Jedit"
        },
        {
            "id":2,
            "webformatURL":"https://wx1.sinaimg.cn/orj360/ecf58dbdgy1fkbwt857ujj20k00ti78l.jpg",
            "webformatWidth":640,
            "webformatHeight":640,
            "largeImageURL":"https://wx1.sinaimg.cn/mw1024/ecf58dbdgy1fkbwt857ujj20k00ti78l.jpg",
            "favorites":0,
            "user":"9Jedit"
        },
        {
            "id":3,
            "webformatURL":"https://wx1.sinaimg.cn/orj360/ecf58dbdgy1fkbwt8i4gjj20k00tpdht.jpg",
            "webformatWidth":640,
            "webformatHeight":640,
            "largeImageURL":"https://wx1.sinaimg.cn/mw1024/ecf58dbdgy1fkbwt8i4gjj20k00tpdht.jpg",
            "favorites":0,
            "user":"9Jedit"
        },
        {
            "id":4,
            "webformatURL":"https://wx1.sinaimg.cn/orj360/ecf58dbdgy1fkbwt91p2aj20k00t1q61.jpg",
            "webformatWidth":640,
            "webformatHeight":640,
            "largeImageURL":"https://wx1.sinaimg.cn/mw1024/ecf58dbdgy1fkbwt91p2aj20k00t1q61.jpg",
            "favorites":0,
            "user":"9Jedit"
        },
        {
            "id":5,
            "webformatURL":"https://wx1.sinaimg.cn/orj360/ecf58dbdgy1fkbwt9qsx4j20k00sewi8.jpg",
            "webformatWidth":640,
            "webformatHeight":640,
            "largeImageURL":"https://wx1.sinaimg.cn/mw1024/ecf58dbdgy1fkbwt9qsx4j20k00sewi8.jpg",
            "favorites":0,
            "user":"9Jedit"
        },
        {
            "id":6,
            "webformatURL":"https://wx1.sinaimg.cn/orj360/ecf58dbdgy1fkbwta7torj20k00t7go3.jpg",
            "webformatWidth":640,
            "webformatHeight":640,
            "largeImageURL":"https://wx1.sinaimg.cn/mw1024/ecf58dbdgy1fkbwta7torj20k00t7go3.jpg",
            "favorites":0,
            "user":"9Jedit"
        },
        {
            "id":7,
            "webformatURL":"https://wx1.sinaimg.cn/orj360/ecf58dbdgy1fkbwtanjrmj20k00se0wp.jpg",
            "webformatWidth":640,
            "webformatHeight":640,
            "largeImageURL":"https://wx1.sinaimg.cn/mw1024/ecf58dbdgy1fkbwtanjrmj20k00se0wp.jpg",
            "favorites":0,
            "user":"9Jedit"
        },
        {
            "id":8,
            "webformatURL":"https://wx1.sinaimg.cn/orj360/ecf58dbdgy1fkbwtb23d6j20k00sutbl.jpg",
            "webformatWidth":640,
            "webformatHeight":640,
            "largeImageURL":"https://wx1.sinaimg.cn/mw1024/ecf58dbdgy1fkbwtb23d6j20k00sutbl.jpg",
            "favorites":0,
            "user":"9Jedit"
        },
        {
            "id":9,
            "webformatURL":"https://wx1.sinaimg.cn/orj360/ecf58dbdgy1fkbwtbo3iij20iw0qtwhe.jpg",
            "webformatWidth":640,
            "webformatHeight":640,
            "largeImageURL":"https://wx1.sinaimg.cn/mw1024/ecf58dbdgy1fkbwtbo3iij20iw0qtwhe.jpg",
            "favorites":0,
            "user":"9Jedit"
        }
    ]
}